[
    {
        "n":1,
        "titulo":"Producci\u00f3n de proyectos culturales en el Centro Cultural Universitario \u201cPaco Urondo\u201d",
        "fecha_inscripcion":"27\/02\/2025 al 07\/03\/2025",
        "cursada":"Jueves 18 a 22 hs",
        "lugar":"Sede 25 de mayo, Centro Cultural Universitario \"Paco Urondo\" (25 de Mayo 201, CABA)",
        "docentes":"Nicol\u00e1s Lisoni y Alejandro Olivera",
        "equipo_docente":"Lara Gorfinkiel, Gabriel Lewin, Roc\u00edo Villar",
        "programa":"https:\/\/drive.google.com\/file\/d\/1ef7y8QQXaIix_fkMQ9RmZMJTXXBRvP3P\/view?usp=sharing",
        "carreras":"Artes, Educaci\u00f3n, Edici\u00f3n, Antropolog\u00eda, Bibliotecolog\u00eda, Filosof\u00eda",
        "presentacion":"El seminario pretende poner en movimiento los aprendizajes obtenidos por lxs estudiantes durante la cursada de sus diferentes carreras y hacerlos entrar en di\u00e1logo con diversas instancias de la producci\u00f3n y gesti\u00f3n cultural, otorg\u00e1ndole valor a los saberes surgidos de esas sinergias y encontrando la posibilidad de generar conocimiento a partir de la reflexi\u00f3n y la acci\u00f3n en la pr\u00e1ctica de hacer cultural. Este seminario se llevar\u00e1 a cabo en la Sede 25 de mayo, Centro Cultural Universitario \"Paco Urondo\" (25 de Mayo 201, CABA)"
    }
]
